<?xml version="1.0" encoding="UTF-8"?>
<Container>
    
    <Wall>
        <asset>
	        <name>Simpleton Walls</name>
	        <path>atlas/Walls/SimpletonWalls.atlas</path>
	    </asset>
    </Wall>
    <Object>
        <asset>
            <name>Containers(Dumpster)</name>
            <path>atlas/Objects/Dumpsters.atlas</path>
        </asset>
    </Object>
    <Floor>
        <asset>
            <name>Test</name>
            <path>atlas/Floors/SimpletonFloors.atlas</path>
        </asset>
    </Floor>
</Container>